eda/CSI.py
eda/IV.py
eda/__init__.py
eda_data-0.0.1.dist-info/METADATA
eda_data-0.0.1.dist-info/WHEEL
eda_data-0.0.1.dist-info/top_level.txt
eda_data-0.0.1.dist-info/RECORD
