Metadata-Version: 2.1
Name: eda-data
Version: 0.0.1
Summary: EDA Package
Author: Gaurav Tyagi
Requires-Dist: pandas
Requires-Dist: numpy
Requires-Dist: scipy
Requires-Dist: tqdm
